{
    "success": true,
    "result": [
        {
            "id": "1",
            "title": "1. Cybersecurity Essentials for the Digital World",
            "details": "<p><span style=\"background-color: rgb(255, 255, 255); color: rgb(0, 0, 0);\">This lecture covers fundamental cybersecurity principles, common threats, and practical strategies to protect digital assets.</span></p>",
            "target": "IT professionals, students, and small business owners",
            "prerequisite": "Basic knowledge of IT systems",
            "type": "LECTURE",
            "format": "ONSITE",
            "capacity": 50,
            "dates": [
                {
                    "date": {
                        "startDateTime": "2025-12-05T01:00:00.000",
                        "endDateTime": "2025-12-05T09:00:00.000"
                    },
                    "venueId": []
                }
            ],
            "stepperStatus": 2,
            "meetingUrl": null,
            "content": null,
            "registrationUrl": null,
            "registrationStatus": false,
            "venueStatus": 1,
            "rejectReason": "",
            "instructorName": "testUser",
            "instructorBio": "JohnDoe@gmail.com",
            "instructorAvatar": "",
            "instructorFamiliarity": "SIT STUDENT",
            "coverImage": "",
            "createdWhen": "2024-11-30T20:12:11.618",
            "updatedWhen": "2024-11-30T20:12:11.618",
            "owner": "1",
            "coOwners": [],
            "published": true
        },
        {
            "id": "2",
            "title": "2. Introduction to Cloud Computing",
            "details": "<p><span style=\"background-color: rgb(255, 255, 255); color: rgb(0, 0, 0);\">An overview of cloud computing concepts, service models (IaaS, PaaS, SaaS), and its applications in modern IT environments.</span></p>",
            "target": "IT professionals, students, and businesses exploring cloud solutions",
            "prerequisite": "Basic knowledge of IT infrastructure",
            "type": "LECTURE",
            "format": "ONLINE",
            "capacity": 50,
            "dates": [
                {
                    "date": {
                        "startDateTime": "2025-12-04T17:00:00",
                        "endDateTime": "2025-12-04T17:00:00"
                    },
                    "venueId": []
                },
                {
                    "date": {
                        "startDateTime": "2025-12-05T17:00:00",
                        "endDateTime": "2025-12-05T17:00:00"
                    },
                    "venueId": []
                }
            ],
            "stepperStatus": 2,
            "meetingUrl": null,
            "content": null,
            "registrationUrl": null,
            "registrationStatus": false,
            "venueStatus": 1,
            "rejectReason": "",
            "instructorName": "Natdanai Nitipan",
            "instructorBio": "c3bosskung@gmail.com",
            "instructorAvatar": "https://lh3.googleusercontent.com/a/ACg8ocLi7iT0Hu6LMAif9P8UyNpb2ga-yHhWwqy8RW9cjaQKAjDDjubk=s96-c",
            "instructorFamiliarity": "SIT STUDENT",
            "coverImage": "",
            "createdWhen": "2024-12-01T02:34:03.092",
            "updatedWhen": "2024-12-01T02:34:51.146",
            "owner": "672857b92c95ec2252ec6b90",
            "coOwners": [],
            "published": true
        }
    ],
    "error": null
}